osbot_markdown/__init__.py
osbot_markdown/markdown/Markdown_Examples.py
osbot_markdown/markdown/Markdown_Parser.py
osbot_markdown/markdown/__init__.py
osbot_markdown/markdown/md__block_processors/Block_Processor__Mermaid.py
osbot_markdown/markdown/md__block_processors/__init__.py
osbot_markdown/markdown/md__extensions/Extension__Chat_Bot.py
osbot_markdown/markdown/md__extensions/Extension__IFrame.py
osbot_markdown/markdown/md__extensions/Extension__Mermaid.py
osbot_markdown/markdown/md__extensions/Extension__QUnit.py
osbot_markdown/markdown/md__extensions/Extension__Video.py
osbot_markdown/markdown/md__extensions/__init__.py
osbot_markdown/markdown/md__patterns/Pattern__Video.py
osbot_markdown/markdown/md__patterns/__init__.py
osbot_markdown/markdown/md__pre_processors/Pre_Processor__Chat_Bot.py
osbot_markdown/markdown/md__pre_processors/Pre_Processor__IFrame.py
osbot_markdown/markdown/md__pre_processors/Pre_Processor__QUnit.py
osbot_markdown/markdown/md__pre_processors/__init__.py
osbot_markdown/utils/Version.py
osbot_markdown/utils/__init__.py
osbot_markdown/version
osbot_markdown-0.1.3.dist-info/LICENSE
osbot_markdown-0.1.3.dist-info/METADATA
osbot_markdown-0.1.3.dist-info/WHEEL
osbot_markdown-0.1.3.dist-info/RECORD
